[
  {
    "title": "側近の寄稿　「最近の日記帳から　（１）」",
    "date": "昭和28年7月15日",
    "content": "<b><font size=\"+2\">側近の寄稿　「最近の日記帳から　（１）」</font></b>　瓢箪　（昭和28年7月15日発行）<br/>\n<br/>「四月十四日午後、明主様が箱根美術館へおいでになるとの報を耳にし、私も近くの町に住む者としてじっとしておれない感動を覚えお出迎えさして戴くべく強羅へ上った。<br/>\n<br/>もっとも私には前日関西からの御帰還を神経痛で脚が立たず松葉杖をついて熱海駅へお出迎え申し上げたところ、おかげさまで帰りには杖なしで歩ける程楽にして戴いたので、今日も丁度幸い御光に触れさして頂き、もう一そう快くしていただきたいという勝手な願望も幾分あった。<br/>\n<br/>強羅に着くと、今日の陳列の御用を仰せつかったという専門家のＹ氏が、疲れた顔してやって来るのに出会した<br/>\n<br/>「京都に一週間もいて明主様のお伴をしてあちこち廻り、今日着いたばかりでフラフラのところへ又御用ですよ。<br/>\n<br/>それにしても明主様はあのお年でよくもあんなに身体がお続きになる、全く不思議でならぬ。<br/>\n<br/>とても吾々若い者は、どんなにしても敵いません」と、それでもお使い戴く喜びを面にうかべながら語っている。<br/>\n<br/>それは私も長年経験した感歎の悲鳴である。<br/>\n<br/>又明主様はいつも若い者がノロイので私の方で加減していると仰せられる程の御元気も、世の為の重要事に対してはどんな御骨折も御いといにならぬ事も、<br/>\n<br/>何事にも速刻主義であられ、すべて極めて早いうちから御準備せられることなども充分知っていながら、<br/>\n<br/>まさか長途の御旅行から、御帰り早々の今日御着手になろうとは、実は私も大いに驚いていたのであるが、<br/>\n<br/>美術館係員の人々も皆意外だったらしく何か狼狽の色が感ぜられた。<br/>\n<br/>\n<br/>やがて明主様は御着きになり、いつもと変らぬ素早く軽い御足どりで、美術館へお入りになった。<br/>\n<br/>何の御用もない私は、せめてお仕事のお邪魔にならぬようにありたいと苑内をブラブラしていたものの、<br/>\n<br/>やはり少しでも御光に近く接していたい、そして何ともいえぬキビキビした御指図ぶりを拝し、<br/>\n<br/>この愚鈍にも智慧の光を賜わりたいという気持を制え難く、図々しくもとうとう館内に入り、暫くの間拝観さして戴いたのである。<br/>\n<br/>明主様は煙草をお吹かしになりながら、全く新しくケースの配置から、予め運ばれた御指定の美術品の陳列まで御指図をなされている。<br/>\n<br/>それはさしてお考えになるという御様子も拝されず、すでに大体でき上ってる御構図のまま形象化されるかの様に極めて御気軽にそうして如何にもお楽しそうになされている。<br/>\n<br/>私は堪らなく嬉しくなる、明主様のお楽しみの御気持そのままが館内に充ち満つるのか何ともいえぬ楽しく嬉しく香り高い芸術境の雰囲気が漂うている。<br/>\n<br/>それは最もお好みになる芸術のお仕事としてのお楽しみであり、この偉大な美術館によって大勢の人々を楽しましめ、天国に遊ばせたもう神の大愛でもあろう。<br/>\n<br/>そして係員の人々もきわめて身軽くこの快よい雰囲気の力に自から動かされているようにみえ、その緊張した面持にも御指図のまま動くいそいそした喜びの血潮を全身に沸（たぎ）らしているのが、惻々（そくそく）として胸に感ぜられてくるのである。<br/>\n<br/>そしてあの狭い室内に十名余の人々が絶えず出入りして貴重な美術品を動かしたり、ガラス張りのケースを運び入れたり出したりしているのを見ていると、とてもスリルを感じ思わず緊張する。<br/>\n<br/>それでいて何の遅滞も過失もなく迅速に進捗してゆく状は、明主様の御指図にして初めてなされ得る御事である。<br/>\n<br/>しかも又、すべての美術品は格位色調形状等による配置の順序の正妙、間隔、高さ、置方等による位置の適確など、<br/>\n<br/>あらゆる点を最高の常識によって勘案結合されてなされている寸分のスキのない神技も誰にもできぬ事であり、<br/>\n<br/>又それと、室内すべてに強い色感なく、観音の心に落着きを与え、無枠のウインド、細枠のケース等も相俟って<br/>\n<br/>美術品の真価を最高度に顕彰せしむる周到言語に絶する装備は悉く明主様によって創成された素晴しい陳列芸術であり、箱根美術館の最高級たる特色の一つとなっている訳である。<br/>\n<br/>\n<br/>さて、私は御指図の光景を拝観していると、われわれの頭でする仕事などは宛かも何世紀か前の人間を突如現代の文化時代につれて来たように、<br/>\n<br/>ただポーッとして生きてるという名ばかりで、いつもフラフラマゴマゴしているに等しい遅鈍極まるものであることをつくずく感じた。<br/>\n<br/>そして御仕事をただ無為に傍観しているのみの自分が申訳ない気もしてついに館外へ御遠慮さしていただいた。<br/>\n<br/>そして私は心の曇りを洗い浄められた爽快を覚え、頭脳もいつの間にかとても冴えていることに気がつき、拝観したことによって私の祈望も、充分叶えて戴いたことを知って感謝し奉った。<br/>\n<br/>やがて明主様をお見送り申し上げ、生き返ったような明るい気持で、帰路に着いたのである。<br/>\n<br/>そうして明主様はその後十八日午後と、二十日午前と二回おいでになっただけで、あれほどの陳列をすっかり終えさせられたのであった。」<br/>\n<br/>\n<hr/>\n<br/>\n<br/>",
    "filename": "omoide3.html"
  },
  {
    "title": "側近の寄稿　「最近の日記帳から　（２）」",
    "date": "昭和28年8月26日",
    "content": "<b><font size=\"+2\">側近の寄稿　「最近の日記帳から　（２）」</font></b>　瓢箪　（昭和28年8月26日発行）<br/>\n<br/>「美術館開館の日、明主様も熱海からおいでになり、所々陳列を御直しになられながら全室を御巡覧になられた。<br/>\n<br/>その御後に従って私達も拝観さして戴いたが、明主様がじっと御見入りになっていると、その美術品の精が浮出て光を放つように思え、<br/>\n<br/>私だけで見る時よりもその真価がズーッとはっきり心に映って来る気がするのも不思議である。<br/>\n<br/>吾々は明主様から折にふれて御教えいただいたり、昨年度々拝観したおかげで、鑑賞の眼もよほど肥えて来た故でもあろうか、<br/>\n<br/>新しく展示されたものには見ていて魂の中心まで射られるような力を感ずるものが数多く確かに去年より優れるとも劣らず、<br/>\n<br/>好事家があっとするような逸品や、人々の眼に触れたことのない素晴しいもののみが並べられているのであろう事が分る。<br/>\n<br/>又昨年は出陳された数も非常に多かったが、今年はかなり成らされており、ゆったりと鑑賞できるし、又美術品も一そう引立って、<br/>\n<br/>その価値の尊さが高まっている私は見終ってから何ともいえぬ快感に満たされ、情操が飛躍的に向上された様な感銘を覚えた。<br/>\n<br/>恐らくは賞めることのない有名な一流美術評論家の某氏が、昨年は幾分の欠点を挙げ得たが今年見た時は一点の非の打所なく、激賞の外すべはなかったとのことであるが、<br/>\n<br/>それは当然すぎることと思うのである。とにかく、昨年よりはるかに素晴しいというのは誰もが一致した感想である。<br/>\n<br/>\n<br/>特に吾々が驚歎に堪えないのは、美術館環境の一大変貌である。<br/>\n<br/>紅葉亭跡へ渓流に添うて建てられた美しい別館と、本館前から自動車路となり広場となり、渓流にかかる橋の完成は、夢想もしなかった天国美を生んで、全体の趣を一変してしまった。<br/>\n<br/>それと流をつくる奇巌怪石、それを彩る花弁や紅葉。そして一面の苔庭等豪壮幽邃（ゆうすい）味わいつきぬ美を窓にみる待合所、それ等建築の全く新様式の近代美と、自然的庭園美とがこの上なくマッチして、<br/>\n<br/>あの広からぬ斜面に得もいえぬ景趣のあらゆる変化をつくり少しも狭隘さがなく陶然たらしめる神技の素晴しさは見る度に味わい深まり讃美尽くるところなく、到底表現の筆をもてぬ程である。<br/>\n<br/>恐らくはこの環境美に接し美術館を見るどんな人でも、真善美の神の御心にふれて魂の目覚めを覚えずにはおれぬであろう。<br/>\n<br/>\n<br/>前日、私は強羅行の電車の中で、最近美術品を御目にかけ始めたという某氏と偶然一緒になり、美術に関する話を種々聞いた。<br/>\n<br/>その人は「美術品を集める程のどんな人でも贋物をつかまぬ人は一人もない。<br/>\n<br/>ところが明主様に限って一点の贋物もお採りになっていないのは実に驚いたものですね」と真偽を即座に御鑑定になる御眼力の卓越さにはよほど舌を巻いているらしく、幾度か感歎の声を発していた。<br/>\n<br/>全くそれは世に例のないことであって、普通一人前の鑑定眼を備える為には、よほど数多くの贋物をつかむものだそうである。<br/>\n<br/>なお大抵の好事家や専門家の鑑定眼は一ないし数種目に偏るもので、中国陶器なり日本陶器なり、その得意の部門の鑑定には大いに優れているが、<br/>\n<br/>他の部門になるとズーッと劣ったり、まるで分らぬ人が多いそうであるが、<br/>\n<br/>明主様におかれては、絵画、彫刻、蒔絵、陶器等から、最も困難とされている銅器に至るまで、<br/>\n<br/>洋の東西、新古を問わず、どんな種類にでも、優れた鑑賞眼をお持ちになり、<br/>\n<br/>しかも大抵は即座になされるのであるからただただ神智と申し上ぐる外はなく、<br/>\n<br/>それは箱根美術館を一見すれば誰しも容易に肯ける訳である。<br/>\n<br/>又今まで箱根美術館を評する記事を読む度に、当然大いに推賞すべき逸品を見落したのではないかと思わるる程の偏頗が感ぜられることがよくあった。<br/>\n<br/>これによってもすべての部門に渉って透徹せる鑑賞眼をもつ人はやはり容易にないものかといつも思わされるのである。<br/>\n<br/>\n<br/>その人は又、自分のお届けする美術品が箱根美術館に出品される事に非常な名誉を感じている様であった<br/>\n<br/>どんな美術館でも優れた名品は極僅かで、大抵は如何わしいものやいわゆるゴミに近いもの甚だしいのは贋物も混っている場合さえあるが<br/>\n<br/>何といってもこの美術館だけは逸品中の逸品でなくては出品されない。<br/>\n<br/>このように高級な美術館へ、自分の手に入れたものが、出品の所を得るのは何よりの喜びでもある訳である。<br/>\n<br/>又、明主様が美術品をお集めになるのは国家の為世界の為であって、<br/>\n<br/>今迄容易に見る事のできなかった名宝を惜し気もなく常時一般公開せられ、<br/>\n<br/>一人も多くの人を楽しませ真の美術館の在り方を示され様となさるそのお気持にも深く感動している。<br/>\n<br/>その様な感動から、これはと思うものは必ず、第一に明主様に御覧に入れるようにしていると語っていた。<br/>\n<br/>箱根美術館は最高品のみが集っているのは勿論神力による驚異の大奇蹟であるが、<br/>\n<br/>その奇蹟に動かさるる人々の気持には右のような感動も自ら働いているのであろうと考えたのである。」<br/>\n<br/>\n<hr/>\n<br/>\n<br/>",
    "filename": "omoide3.html"
  }
]